[{
  "_id": {
    "$oid": "631db21d20ffde605a7daf23"
  },
  "shippingInfo": {
    "address": "3737 PACIFIC COAST HIGHWAY",
    "city": "TORONTO",
    "state": "CA",
    "country": "USA",
    "pinCode": 90505,
    "phoneNo": {
      "$numberLong": "653423982930"
    }
  },
  "orderItems": [
    {
      "name": "4",
      "price": 360,
      "quantity": 1,
      "image": "test.com",
      "product": {
        "$oid": "6313272ca655867517351320"
      },
      "_id": {
        "$oid": "631db21d20ffde605a7daf24"
      }
    }
  ],
  "user": {
    "$oid": "6313da51e5a4f6986801f287"
  },
  "paymentInfo": {
    "id": "dfeouwe34932",
    "status": "succeeded"
  },
  "paidAt": {
    "$date": {
      "$numberLong": "1662890525331"
    }
  },
  "itemsPrice": 350,
  "taxPrice": 20,
  "shippingPrice": 100,
  "totalPrice": 420,
  "orderStatus": "Processing",
  "createdAt": {
    "$date": {
      "$numberLong": "1662890525000"
    }
  },
  "__v": 0
}]